CHANGES.txt
CONTRIBUTORS.txt
setup.py
spats/LGPL.txt
spats/README.txt
spats/SimplePageTemplateServer.py
spats/__init__.py
spats/browser.py
spats/example.py
spats/formats.py
spats/mfcembed.py
spats/server.py
spats/splash.py
spats/taskbar.py
spats/util.py
spats/wxembed.py
spats.egg-info/PKG-INFO
spats.egg-info/SOURCES.txt
spats.egg-info/dependency_links.txt
spats.egg-info/not-zip-safe
spats.egg-info/requires.txt
spats.egg-info/top_level.txt
spats/base/index.pt
spats/base/template.pt
spats/base/img/error.gif
spats/base/img/splash.bmp
spats/docs/overview.rst
spats/errors/302.pt
spats/errors/403.pt
spats/errors/404.pt
spats/errors/500.pt
spats/schema/__init__.py
spats/schema/schema.py
spats/schema/validation.py
spats/schema/templates/boolean.pt
spats/schema/templates/choice.pt
spats/schema/templates/password.pt
spats/schema/templates/registry.pt
spats/schema/templates/text.pt
spats/schema/templates/text_lines.pt
spats/schema/tests/schema.ini
spats/schema/tests/start.py
spats/schema/tests/test.py
spats/schema/tests/html/index.pt
spats/schema/tests/scripts/load.py
spats/scripts/example.py