Metadata-Version: 1.0
Name: spats
Version: 0.1
Summary: Spats or Simple PAge Template Server is an attempt to make a simple little Page Template Server that can be used by everyone
Home-page: http://enfoldsystems.com/
Author: Sidnei da Silva
Author-email: sidnei at enfoldsystems dot com
License: LGPL
Keywords: server template tal
Platform: UNKNOWN
Classifier: Environment :: Web Environment
Classifier: Intended Audience :: Developers
Classifier: Topic :: Software Development :: User Interfaces
Classifier: Topic :: Software Development :: Libraries :: Python Modules
Classifier: License :: OSI Approved :: GNU Library or Lesser General Public License (LGPL)
